{
    "release.version"  : "0.5.0",
    "release.name"     : "Caulked Snack",
    "release.day"      : "Tuesday",
    "release.date"     : "20 November 2007",
    "release.nextdate" : "18 December 2007",

    "web.root"         : "http://parrotcode.org/",
    "web.source"       : "source.html",
    "web.openpatches"  : "openpatches.html",
    "web.repository"   : "https://svn.perl.org/parrot/trunk/",

    "bugday.day"       : "Saturday",
    "bugday.date"      : "15 December 2007",

    "rt.root"          : "https://rt.perl.org/rt3/",
    "rt.tracking"      : "Ticket/Display.html?id=38967",
    "rt.saved_search"  : "http://xrl.us/bbjr4",

    "wiki.root"        : "http://www.perlfoundation.org/parrot/index.cgi?",
    "wiki.bugday"      : "bug_day_2007_12_15",

    "cpan.search"      : "http://search.cpan.org/dist/parrot",
    "subversion.root"  : "http://subversion.tigris.org/",
    "svk.root"         : "http://svk.bestpractical.com/"
}
