{
    "release.version"  : "3.6.0",
    "release.name"     : "Pájaros del Caribe",
    "release.day"      : "Tuesday",
    "release.date"     : "19 July 2011",
    "release.nextdate" : "16 August 2011",

    "web.root"         : "http://parrot.org/",
    "web.source"       : "download",
    "web.openpatches"  : "openpatches.html",
    "web.repository"   : "https://github.com/parrot/parrot",
    "web.org_root"    :  "https://github.com/parrot",

    "bugday.day"       : "Saturday",
    "bugday.date"      : "13 August 2011",

    "wiki.root"        : "https://trac.parrot.org/parrot/wiki/",
    "wiki.bugday"      : "bug_day_2011_08_13",

    "ftp.path"         : "ftp://ftp.parrot.org/pub/parrot/releases/devel/3.6.0/"
}
